bendercoder-1.2.1.dist-info/METADATA
bendercoder-1.2.1.dist-info/RECORD
bendercoder-1.2.1.dist-info/WHEEL
bendercoder-1.2.1.dist-info/top_level.txt
decoder/__init__.py
decoder/decoder.py
decoder/error.py
encoder/__init__.py
encoder/encoder.py
encoder/error.py
