Metadata-Version: 2.1
Name: bendercoder
Version: 1.2.1
Summary: Library for encoding and decoding bencode data.
Home-page: https://github.com/m19t12/bendercoder
Author: Manolis Tsoukalas
Author-email: emmtsoukalas@gmail.com
License: UNKNOWN
Platform: UNKNOWN
Classifier: Programming Language :: Python :: 3
Classifier: License :: OSI Approved :: GNU General Public License v3 (GPLv3)
Classifier: Operating System :: OS Independent
